facebook_account_checker/__init__.py
facebook_account_checker/checker.py
tests/__init__.py
tests/test_checker.py
facebook_account_checker-0.1.dist-info/METADATA
facebook_account_checker-0.1.dist-info/WHEEL
facebook_account_checker-0.1.dist-info/top_level.txt
facebook_account_checker-0.1.dist-info/RECORD
